pycourt/__init__.py
pycourt/cli.py
pycourt/config/config.py
pycourt/config/exempt.py
pycourt/config/judges_texts.py
pycourt/config/read_toml.py
pycourt/config/yaml_paths.py
pycourt/judge.py
pycourt/laws/__init__.py
pycourt/laws/ac001.py
pycourt/laws/bc001.py
pycourt/laws/di001.py
pycourt/laws/ds001.py
pycourt/laws/dt001.py
pycourt/laws/hc001.py
pycourt/laws/ll001.py
pycourt/laws/ou001.py
pycourt/laws/pc001.py
pycourt/laws/re001.py
pycourt/laws/sk001.py
pycourt/laws/tc001.py
pycourt/laws/tp001.py
pycourt/laws/uw001.py
pycourt/laws/vt001.py
pycourt/loader.py
pycourt/models.py
pycourt/utils.py
pycourt/yaml/config.yaml
pycourt/yaml/judges_text.en.yaml
pycourt/yaml/judges_text.zh.yaml
pycourt-0.1.1.dist-info/METADATA
pycourt-0.1.1.dist-info/WHEEL
pycourt-0.1.1.dist-info/entry_points.txt
pycourt-0.1.1.dist-info/licenses/LICENSE.md
pycourt-0.1.1.dist-info/RECORD
