Metadata-Version: 2.4
Name: pycourt
Version: 0.1.1
Summary: Production-grade code audit engine for AI-generated Python code. AST-powered, rule-based quality enforcement.
License-Expression: MIT
License-File: LICENSE.md
Keywords: ai,code-quality,static-analysis,ast,linting,architecture,python,audit,rules,production
Author: PythonCourt Team
Author-email: johorner@pythoncourt.com
Requires-Python: >=3.11,<4.0
Classifier: Topic :: Scientific/Engineering :: Artificial Intelligence
Classifier: Topic :: Software Development :: Quality Assurance
Classifier: Development Status :: 4 - Beta
Classifier: Intended Audience :: Developers
Classifier: Intended Audience :: Science/Research
Classifier: Topic :: Software Development :: Testing
Classifier: Topic :: Software Development :: Libraries :: Python Modules
Classifier: Topic :: Software Development :: Version Control :: Git
Classifier: Programming Language :: Python :: 3
Classifier: Programming Language :: Python :: 3.11
Classifier: Programming Language :: Python :: 3.12
Classifier: Programming Language :: Python :: 3.13
Classifier: Programming Language :: Python :: 3.14
Classifier: Framework :: Pytest
Classifier: Typing :: Typed
Classifier: Natural Language :: English
Classifier: Natural Language :: Chinese (Simplified)
Requires-Dist: PyYAML (>=6.0.0,<7.0.0)
Requires-Dist: pydantic (>=2.9.0,<3.0.0)
Project-URL: Bug Tracker, https://github.com/PythonCourt/PyCourt/issues
Project-URL: Documentation, https://pythoncourt.com/docs
Project-URL: Discussions, https://github.com/PythonCourt/PyCourt/discussions
Project-URL: Homepage, https://pythoncourt.com
Project-URL: Repository, https://github.com/PythonCourt/PyCourt
